mir/git/__init__.py
mir.git-2.1.1.dist-info/METADATA
mir.git-2.1.1.dist-info/RECORD
mir.git-2.1.1.dist-info/WHEEL
mir.git-2.1.1.dist-info/top_level.txt
