Metadata-Version: 2.1
Name: mir.git
Version: 2.1.1
Summary: Python interface to Git
Home-page: https://github.com/darkfeline/mir-git
Author: Allen Li
Author-email: darkfeline@felesatra.moe
License: UNKNOWN
Platform: UNKNOWN
Classifier: Development Status :: 5 - Production/Stable
Classifier: Intended Audience :: Developers
Classifier: License :: OSI Approved :: Apache Software License
Classifier: Programming Language :: Python :: 3.6
Requires-Python: ~=3.6
